advys-0.1.2.dist-info/licenses/LICENSE
automacoes/__init__.py
automacoes/email_smtp.py
automacoes/funcoes_pyautogui.py
configuracoes/__init__.py
configuracoes/config_logs.py
estrutura/__init__.py
estrutura/atualiza_caminhos.py
estrutura/atualiza_imagens.py
estrutura/caminhos.py
estrutura/config.py
estrutura/estrutura_dir.json
estrutura/imagens.py
estrutura/utils.py
validadores/__init__.py
validadores/arquivo.py
validadores/emal.py
validadores/senha.py
advys-0.1.2.dist-info/METADATA
advys-0.1.2.dist-info/WHEEL
advys-0.1.2.dist-info/top_level.txt
advys-0.1.2.dist-info/RECORD
