Metadata-Version: 2.4
Name: advys
Version: 0.1.2
Summary: Directories structure
Author-email: Chen <chenpsilva@gmail.com>
Classifier: Programming Language :: Python :: 3
Classifier: License :: OSI Approved :: MIT License
Classifier: Operating System :: OS Independent
Requires-Python: >=3.10
License-File: LICENSE
Dynamic: license-file
